{
    "timestamp": "2026-05-01T00:00:00",
    "type": "Technology",
    "data": {
        "rd_staff": 180519,
        "patents": {
            "total": 14211,
            "filed_this_year": 4061,
            "by_category": {
                "Battery_Technology": 4519,
                "Automotive_Electronics": 3392,
                "ADAS_Autonomous": 3108,
                "Manufacturing_Process": 2210,
                "Energy_Storage": 1307
            },
            "international": {
                "US": 2244,
                "Europe": 1924,
                "Japan": 1091,
                "Other": 787
            }
        },
        "rd_investment": {
            "total_billion_cny": 41.412666345213005,
            "by_division": {
                "Automotive": 8.2,
                "Battery": 6.1,
                "Electronics": 2.8,
                "Energy_Storage": 1.4
            },
            "by_stage": {
                "Basic_Research": 0.15,
                "Applied_Research": 0.35,
                "Development": 0.4,
                "Testing_Validation": 0.1
            }
        },
        "research_centers": {
            "Shenzhen_HQ": {
                "staff": 37404,
                "focus": [
                    "Battery_Chemistry",
                    "Power_Electronics"
                ],
                "budget_billion_cny": 9.853108221313198,
                "breakthrough_probability": 0.15
            },
            "Shanghai_Auto": {
                "staff": 27424,
                "focus": [
                    "ADAS",
                    "Autonomous_Driving",
                    "Vehicle_Integration"
                ],
                "budget_billion_cny": 8.235715324031176,
                "breakthrough_probability": 0.15
            },
            "Beijing_AI": {
                "staff": 19402,
                "focus": [
                    "AI_Algorithms",
                    "Machine_Learning",
                    "Data_Analytics"
                ],
                "budget_billion_cny": 6.621492544938828,
                "breakthrough_probability": 0.15
            },
            "Xian_Manufacturing": {
                "staff": 14532,
                "focus": [
                    "Process_Innovation",
                    "Automation",
                    "Quality_Systems"
                ],
                "budget_billion_cny": 3.8573145252830243,
                "breakthrough_probability": 0.022728849453820525
            },
            "International_Labs": {
                "staff": 9452,
                "focus": [
                    "Global_Standards",
                    "Localization",
                    "Partnerships"
                ],
                "budget_billion_cny": 2.8536845695458446,
                "breakthrough_probability": 0.00016108651619899458
            }
        },
        "innovation_pipeline": {
            "concept_stage": [
                {
                    "name": "Wireless_Charging_Highway",
                    "progress": 0.935491339164662,
                    "potential_impact": 0.45
                },
                {
                    "name": "Sustainable_Material_Recovery",
                    "progress": 0.9429319008212269,
                    "potential_impact": 0.4938669039649072
                },
                {
                    "name": "Edge_AI_Vehicle_Computing",
                    "progress": 0.7784922898426178,
                    "potential_impact": 0.3337900985758048
                },
                {
                    "name": "Bio_Inspired_Battery_Design",
                    "progress": 0.6759237320680912,
                    "potential_impact": 0.4465567514709283
                },
                {
                    "name": "Edge_AI_Vehicle_Computing",
                    "progress": 0.5106945680235332,
                    "potential_impact": 0.2036223369947071
                },
                {
                    "name": "Bio_Inspired_Battery_Design",
                    "progress": 0.5492505973539462,
                    "potential_impact": 0.3534218619090975
                },
                {
                    "name": "Quantum_Dot_Solar_Integration",
                    "progress": 0.5187842679702904,
                    "potential_impact": 0.4694744508597357
                },
                {
                    "name": "Next_Gen_Silicon_Anode",
                    "progress": 0.14660939864565578,
                    "potential_impact": 0.26099513844501576
                },
                {
                    "name": "Sustainable_Material_Recovery",
                    "progress": 0.12181627124755443,
                    "potential_impact": 0.27859588709965066
                }
            ],
            "development_stage": [
                {
                    "name": "AI_Predictive_Maintenance",
                    "progress": 0.44446686520020817,
                    "potential_impact": 0.2
                },
                {
                    "name": "Solid_State_Battery_Gen3",
                    "progress": 0.14049134128581334,
                    "potential_impact": 0.35
                }
            ],
            "testing_stage": [
                {
                    "name": "Blade_Battery_2.0",
                    "progress": 0.7832380624170351,
                    "potential_impact": 0.3
                },
                {
                    "name": "LFP_Energy_Density_Plus",
                    "progress": 0.7418716437950537,
                    "potential_impact": 0.25
                },
                {
                    "name": "Level4_Autonomous_Stack",
                    "progress": 0.7502853538632763,
                    "potential_impact": 0.4
                }
            ]
        },
        "technology_partnerships": {
            "Universities": {
                "Tsinghua": {
                    "projects": 12,
                    "budget_million_cny": 120
                },
                "MIT": {
                    "projects": 9,
                    "budget_million_cny": 125.60834398530136
                },
                "Stanford": {
                    "projects": 5,
                    "budget_million_cny": 114.85189355140798
                },
                "Cambridge": {
                    "projects": 1,
                    "budget_million_cny": 66.6987653449698
                }
            },
            "Industry": {
                "NVIDIA": {
                    "focus": "AI_Computing",
                    "investment_million_cny": 501.1845512275268
                },
                "Qualcomm": {
                    "focus": "Automotive_Chips",
                    "investment_million_cny": 512.8538546711094
                },
                "Bosch": {
                    "focus": "Sensor_Technology",
                    "investment_million_cny": 375.7203616249593
                }
            }
        },
        "competitive_intelligence": {
            "Tesla": {
                "patent_activity": "very_high",
                "focus_areas": [
                    "FSD",
                    "Battery_Manufacturing"
                ]
            },
            "Toyota": {
                "patent_activity": "high",
                "focus_areas": [
                    "Solid_State",
                    "Hydrogen"
                ]
            },
            "Volkswagen": {
                "patent_activity": "high",
                "focus_areas": [
                    "Platform_Integration",
                    "Software"
                ]
            },
            "CATL": {
                "patent_activity": "medium",
                "focus_areas": [
                    "Battery_Chemistry",
                    "Manufacturing"
                ]
            }
        },
        "innovation_metrics": {
            "time_to_market_months": 24.5369759166608,
            "success_rate": 0.85,
            "patent_citation_index": 3.1435535858141366,
            "technology_transfer_rate": 0.9,
            "rd_efficiency_score": 0.5277522904285875
        }
    },
    "performance_metrics": {
        "rd_investment": 41.412666345213005,
        "patent_portfolio": {
            "total_patents": 14211,
            "annual_filing_rate": 4061,
            "international_coverage": 6046
        },
        "innovation_pipeline": {
            "total_projects": 14,
            "avg_progress": 0.5743105451213546,
            "breakthrough_potential": 0.342165959237132
        },
        "research_capability": {
            "total_rd_staff": 180519,
            "research_centers": 5,
            "partnership_strength": 7
        },
        "innovation_efficiency": {
            "time_to_market_months": 24.5369759166608,
            "success_rate": 0.85,
            "patent_citation_index": 3.1435535858141366,
            "technology_transfer_rate": 0.9,
            "rd_efficiency_score": 0.5277522904285875
        }
    },
    "technology_trends": {
        "battery_energy_density": 3.1691424333881866,
        "autonomous_driving_capability": 4.175680180239913,
        "ai_integration": 2.4979110386488435,
        "manufacturing_automation": 2.7774085184807373,
        "sustainability_focus": 2.68004143497422
    },
    "innovation_history": {
        "monthly_patents": [
            {
                "month": "2025-01-01T00:00:00",
                "patents_filed": 141
            },
            {
                "month": "2025-02-01T00:00:00",
                "patents_filed": 82
            },
            {
                "month": "2025-03-01T00:00:00",
                "patents_filed": 106
            },
            {
                "month": "2025-04-01T00:00:00",
                "patents_filed": 50
            },
            {
                "month": "2025-05-01T00:00:00",
                "patents_filed": 0
            },
            {
                "month": "2025-06-01T00:00:00",
                "patents_filed": 0
            },
            {
                "month": "2025-07-01T00:00:00",
                "patents_filed": 0
            },
            {
                "month": "2025-08-01T00:00:00",
                "patents_filed": 0
            },
            {
                "month": "2025-09-01T00:00:00",
                "patents_filed": 0
            },
            {
                "month": "2025-10-01T00:00:00",
                "patents_filed": 76
            },
            {
                "month": "2025-11-01T00:00:00",
                "patents_filed": 78
            },
            {
                "month": "2025-12-01T00:00:00",
                "patents_filed": 61
            },
            {
                "month": "2026-01-01T00:00:00",
                "patents_filed": 85
            },
            {
                "month": "2026-02-01T00:00:00",
                "patents_filed": 64
            },
            {
                "month": "2026-03-01T00:00:00",
                "patents_filed": 101
            },
            {
                "month": "2026-04-01T00:00:00",
                "patents_filed": 202
            },
            {
                "month": "2026-05-01T00:00:00",
                "patents_filed": 165
            }
        ],
        "breakthrough_timeline": [
            {
                "date": "2025-01-01T00:00:00",
                "innovation": "Cell_to_Pack_Integration",
                "impact": 0.22,
                "commercialization_timeline": 22
            },
            {
                "date": "2025-02-01T00:00:00",
                "innovation": "Advanced_BMS_AI",
                "impact": 0.18,
                "commercialization_timeline": 21
            }
        ],
        "investment_efficiency": [],
        "competitive_position": []
    }
}